paf/__init__.py
paf/address.py
paf/attribute.py
paf/immutable.py
paf/initiator.py
paf/lineable.py
paf/thoroughfare_locality.py
paf/version.py
paf/premises/__init__.py
paf/premises/attribute.py
paf/premises/building_type.py
paf/premises/dependent_premisable.py
paf/premises/exception.py
paf/premises/extender.py
paf/premises/lineable.py
paf/premises/premisable.py
paf/premises/rule000.py
paf/premises/rule001.py
paf/premises/rule010.py
paf/premises/rule011.py
paf/premises/rule100.py
paf/premises/rule101.py
paf/premises/rule110.py
paf/premises/rule111.py
paf/premises/split.py
pypaf-1.0.3.dist-info/LICENSE.txt
pypaf-1.0.3.dist-info/METADATA
pypaf-1.0.3.dist-info/WHEEL
pypaf-1.0.3.dist-info/top_level.txt
pypaf-1.0.3.dist-info/RECORD
