Metadata-Version: 2.2
Name: PyPaf
Version: 1.0.3
Summary: Formats the elements of a Royal Mail Postcode Address File entry
Author-email: John Bard <johnbard@globalnet.co.uk>
License: MIT
Project-URL: Homepage, https://github.com/drabjay/pypaf
Project-URL: Repository, https://github.com/drabjay/pypaf.git
Project-URL: Issues, https://github.com/drabjay/paf/issues
Classifier: Programming Language :: Python :: 3
Classifier: Operating System :: OS Independent
Requires-Python: >=3.8
License-File: LICENSE.txt
